graphql_utils/__init__.py
graphql_utils/multi.py
graphql_utils-0.4.dist-info/LICENSE
graphql_utils-0.4.dist-info/METADATA
graphql_utils-0.4.dist-info/WHEEL
graphql_utils-0.4.dist-info/top_level.txt
graphql_utils-0.4.dist-info/RECORD
