Metadata-Version: 2.1
Name: graphql-utils
Version: 0.4
Summary: Useful function when interacting with GraphQL APIs
Home-page: https://github.com/Mergifyio/graphql-utils
Author: Mergify
License: BSD 3-Clause License
Platform: UNKNOWN
Classifier: Intended Audience :: Developers
Classifier: License :: OSI Approved :: Apache Software License
Classifier: Programming Language :: Python :: 3.9
Classifier: Programming Language :: Python :: 3.10
License-File: LICENSE
Provides-Extra: test
Requires-Dist: pytest ; extra == 'test'
Requires-Dist: pytest-asyncio ; extra == 'test'
